mint_upload/__init__.py
mint_upload/object_storage.py
mint_upload/progress_percentage.py
mint_upload-0.0.2.dist-info/LICENSE
mint_upload-0.0.2.dist-info/METADATA
mint_upload-0.0.2.dist-info/WHEEL
mint_upload-0.0.2.dist-info/top_level.txt
mint_upload-0.0.2.dist-info/RECORD
