Metadata-Version: 2.1
Name: mint-upload
Version: 0.0.2
Summary: Module to upload file into MIC
Home-page: https://github.com/mintproject/mint_upload
Author: Maximiliano Osorio
Author-email: mosorio@isi.edu
License: Apache-2
Platform: UNKNOWN
Classifier: License :: OSI Approved :: Apache Software License
Classifier: Development Status :: 3 - Alpha
Classifier: Programming Language :: Python
Classifier: Programming Language :: Python :: 3
Classifier: Programming Language :: Python :: 3.5
Classifier: Programming Language :: Python :: 3.6
Classifier: Programming Language :: Python :: 3.7
Classifier: Intended Audience :: Science/Research
Classifier: Operating System :: Unix
Requires-Python: >=3.6.0
Requires-Dist: requests (>=2.24.0)
Requires-Dist: boto3 (>=1.15.0)
